CHANGELOG.txt
LICENCE.txt
MANIFEST.in
README.md
setup.py
zedmath/__init__.py
zedmath.egg-info/PKG-INFO
zedmath.egg-info/SOURCES.txt
zedmath.egg-info/dependency_links.txt
zedmath.egg-info/top_level.txt
zedmath/library/__init__.py