Metadata-Version: 2.1
Name: zedmath
Version: 1.0.2
Summary: Math operations
Home-page: https://www.azizbekdev.com
Author: www.AZIZBEKDEV.com
Author-email: azizbekqozoqovinfo@gmail.com
License: UNKNOWN
Platform: UNKNOWN
Classifier: Development Status :: 4 - Beta
Classifier: Intended Audience :: Education
Classifier: Intended Audience :: Developers
Classifier: License :: OSI Approved :: MIT License
Classifier: Operating System :: MacOS :: MacOS X
Classifier: Operating System :: Microsoft :: Windows
Classifier: Operating System :: POSIX
Classifier: Programming Language :: Python :: 3
License-File: LICENCE.txt
